test_common/src/common_fun/__init__.py
test_common/src/common_fun/tools.py
test_common/src/test_steps/__init__.py
test_common/src/test_steps/http_step.py
py_common_func_package-1.0.9.dist-info/METADATA
py_common_func_package-1.0.9.dist-info/WHEEL
py_common_func_package-1.0.9.dist-info/top_level.txt
py_common_func_package-1.0.9.dist-info/RECORD
