Metadata-Version: 2.1
Name: py_common_func_package
Version: 1.0.9
Summary: python test common function
